kubesdk_cli/__init__.py
kubesdk_cli/cli.py
kubesdk_cli/const.py
kubesdk_cli/crd_generator.py
kubesdk_cli/k8s_dataclass_generator.py
kubesdk_cli/k8s_schema_parser.py
kubesdk_cli/open_api_schema.py
kubesdk_cli/py.typed
kubesdk_cli/templates/_resource_list_generics.py
kubesdk_cli/templates/_resource_list_pep695.py
kubesdk_cli/templates/const.py
kubesdk_cli/templates/dataclass.jinja2
kubesdk_cli/templates/init.py
kubesdk_cli/templates/loader.py
kubesdk_cli/templates/registry.py
kubesdk_cli/templates/resource.py
kubesdk_cli-0.3.1.dist-info/METADATA
kubesdk_cli-0.3.1.dist-info/WHEEL
kubesdk_cli-0.3.1.dist-info/entry_points.txt
kubesdk_cli-0.3.1.dist-info/RECORD
