Metadata-Version: 2.4
Name: kubesdk-cli
Version: 0.3.1
Summary: Kubernetes API models and CRD generator
Project-URL: Repository, https://github.com/puzl-cloud/kubesdk
Author-email: Nik Paushkin <nik@puzl.cloud>
License: MIT
Keywords: cli,crd,generator,kubernetes,kubesdk
Classifier: Development Status :: 5 - Production/Stable
Classifier: Intended Audience :: Developers
Classifier: License :: OSI Approved :: MIT License
Classifier: Operating System :: OS Independent
Classifier: Programming Language :: Python
Classifier: Programming Language :: Python :: 3 :: Only
Classifier: Programming Language :: Python :: 3.10
Classifier: Programming Language :: Python :: 3.11
Classifier: Programming Language :: Python :: 3.12
Classifier: Programming Language :: Python :: 3.13
Classifier: Programming Language :: Python :: 3.14
Requires-Python: >=3.10
Requires-Dist: datamodel-code-generator[http]==0.35.0
Requires-Dist: jinja2>=3.1
Requires-Dist: kubesdk<1.0,>=0.3
Requires-Dist: pydantic<3,>=2.4
Requires-Dist: requests==2.32.5
